stitch_ai/__init__.py
stitch_ai/api/__init__.py
stitch_ai/api/client.py
stitch_ai/api/git.py
stitch_ai/api/marketplace.py
stitch_ai/api/memory.py
stitch_ai/api/memory_space.py
stitch_ai/api/user.py
stitch_ai/cli/__init__.py
stitch_ai/cli/git_cli.py
stitch_ai/cli/main.py
stitch_ai/cli/marketplace_cli.py
stitch_ai/cli/memory_cli.py
stitch_ai/cli/user_cli.py
stitch_ai/processors/__init__.py
stitch_ai/processors/memory_processor.py
stitch_ai/processors/text_processor.py
stitch_ai/sdk/__init__.py
stitch_ai/sdk/git.py
stitch_ai/sdk/marketplace.py
stitch_ai/sdk/memory.py
stitch_ai/sdk/memory_space.py
stitch_ai/sdk/user.py
stitch_ai-0.3.11.dist-info/licenses/LICENSE
stitch_ai-0.3.11.dist-info/METADATA
stitch_ai-0.3.11.dist-info/WHEEL
stitch_ai-0.3.11.dist-info/entry_points.txt
stitch_ai-0.3.11.dist-info/top_level.txt
stitch_ai-0.3.11.dist-info/RECORD
