Metadata-Version: 2.4
Name: stitch_ai
Version: 0.3.11
Summary: Stitch AI SDK for managing memory spaces and memories
Home-page: https://github.com/StitchAI/stitch-ai-cli-py
Author: Stitch AI
Classifier: Programming Language :: Python :: 3
Classifier: License :: OSI Approved :: MIT License
Classifier: Operating System :: OS Independent
Requires-Python: >=3.10
License-File: LICENSE
Requires-Dist: requests
Requires-Dist: python-dotenv
Dynamic: author
Dynamic: classifier
Dynamic: description
Dynamic: description-content-type
Dynamic: home-page
Dynamic: license-file
Dynamic: requires-dist
Dynamic: requires-python
Dynamic: summary
